postgres_kernel/__init__.py
postgres_kernel/__main__.py
postgres_kernel/kernel.py
postgres_kernel/version.py
postgres_kernel-0.2.1.dist-info/LICENSE
postgres_kernel-0.2.1.dist-info/METADATA
postgres_kernel-0.2.1.dist-info/WHEEL
postgres_kernel-0.2.1.dist-info/top_level.txt
postgres_kernel-0.2.1.dist-info/RECORD
