Metadata-Version: 2.1
Name: postgres-kernel
Version: 0.2.1
Summary: A PostgreSQL kernel for IPython
Home-page: https://github.com/bgschiller/postgres_kernel
Author: Brian Schiller
Author-email: bgschiller@gmail.com
License: UNKNOWN
Platform: UNKNOWN
Classifier: Framework :: IPython
Classifier: License :: OSI Approved :: BSD License
Classifier: Programming Language :: Python :: 3
Classifier: Topic :: System :: Shells
Requires-Dist: psycopg2 (>=2.6)
Requires-Dist: tabulate (>=0.7.5)
Requires-Dist: jupyter-client
Requires-Dist: ipykernel
